finitelycomputable/idtrust_django/__init__.py
finitelycomputable/idtrust_django/admin.py
finitelycomputable/idtrust_django/apps.py
finitelycomputable/idtrust_django/models.py
finitelycomputable/idtrust_django/services.py
finitelycomputable/idtrust_django/tests.py
finitelycomputable/idtrust_django/urls.py
finitelycomputable/idtrust_django/views.py
finitelycomputable/idtrust_django/migrations/0001_initial.py
finitelycomputable/idtrust_django/migrations/0002_auto_20180311_0154.py
finitelycomputable/idtrust_django/migrations/0003_interaction_user_guess.py
finitelycomputable/idtrust_django/migrations/0004_miscommunication.py
finitelycomputable/idtrust_django/migrations/0005_auto_20210228_1729.py
finitelycomputable/idtrust_django/migrations/0006_journey.py
finitelycomputable/idtrust_django/migrations/0007_strategy_enum.py
finitelycomputable/idtrust_django/migrations/__init__.py
finitelycomputable_idtrust_django-25.7.dist-info/METADATA
finitelycomputable_idtrust_django-25.7.dist-info/WHEEL
finitelycomputable_idtrust_django-25.7.dist-info/entry_points.txt
finitelycomputable_idtrust_django-25.7.dist-info/top_level.txt
finitelycomputable_idtrust_django-25.7.dist-info/RECORD
